MANIFEST.in
README
requirements.txt
setup.py
jsui/__init__.py
jsui/serve.py
jsui.egg-info/PKG-INFO
jsui.egg-info/SOURCES.txt
jsui.egg-info/dependency_links.txt
jsui.egg-info/requires.txt
jsui.egg-info/top_level.txt